shiftregister/shiftregister.v
module shiftregister_4bit (clock , clear,A,E);

 input clock,clear,A;
 output reg E;
 reg B,C,D;

 always @(posedge clock or negedge clear)
  begin 
   if (!clear) begin B<=0; C<=0; D<=0; E<=0; end
   else begin 
         E <= D;
         D <= C;
         C <= B;
         B <= A;
        end
 end
endmodule

shiftregister/test.v
`timescale 10ns/1ns

module shift_test;
  reg clk, clr, in;
  wire out; 
  integer i;

  // Make sure this module is defined somewhere
  shiftregister_4bit SR (clk, clr, in, out);

  // Initial block to set initial values
  initial begin 
    clk = 1'b0;
    clr = 0;
    #2 clr = 1;  // <-- Fixed: #clr=1; is invalid
  end

  // Clock generation every 5 time units (10ns period)
  always #5 clk = ~clk;

  // Input stimulus generation
  initial begin
    #2; // wait 2 time units after simulation starts
    repeat (2) begin
      #10 in = 0;
      #10 in = 0;
      #10 in = 1;
    end
  end

  // Dump waveforms to a .vcd file for GTKWave
  initial begin
    $dumpfile("shift.vcd");
    $dumpvars(0, shift_test);
    #200 $finish;
  end
endmodule

shiftregister/shift.vcd
$date
	Sat Apr 05 14:53:00 2025
$end
$version
	Icarus Verilog
$end
$timescale
	1ns
$end
$scope module shift_test $end
$var wire 1 ! out $end
$var reg 1 " clk $end
$var reg 1 # clr $end
$var reg 1 $ in $end
$scope module SR $end
$var wire 1 % A $end
$var wire 1 & clear $end
$var wire 1 ' clock $end
$var reg 1 ( B $end
$var reg 1 ) C $end
$var reg 1 * D $end
$var reg 1 + E $end
$upscope $end
$upscope $end
$enddefinitions $end
#0
$dumpvars
0+
0*
0)
0(
0'
0&
x%
x$
0#
0"
0!
$end
#20
1#
1&
#50
x(
1"
1'
#100
0"
0'
#120
0$
0%
#150
0(
x)
1"
1'
#200
0"
0'
#250
0)
x*
1"
1'
#300
0"
0'
#320
1$
1%
#350
1(
0*
x+
x!
1"
1'
#400
0"
0'
#420
0$
0%
#450
0(
1)
0+
0!
1"
1'
#500
0"
0'
#550
0)
1*
1"
1'
#600
0"
0'
#620
1$
1%
#650
1(
0*
1+
1!
1"
1'
#700
0"
0'
#750
1)
0+
0!
1"
1'
#800
0"
0'
#850
1*
1"
1'
#900
0"
0'
#950
1+
1!
1"
1'
