registerwithreset/32bitreg.v
//32 x 32 register bank with reset facility

module regbank_v4(rdData1, rdData2, wrdata, sr1, sr2, dr, write, reset, clk);
    input clk, write, reset;
    input [4:0] sr1, sr2, dr; // source and destination register numbers
    input [31:0] wrdata; // data to be written
    output [31:0] rdData1, rdData2; // data to be read from registers
    integer k;


    reg [31:0] regfile [0:31]; // 32 registers of 32 bits each

    assign rdData1 = regfile[sr1]; // read data from source register 1
    assign rdData2 = regfile[sr2]; // read data from source register 2


    always @(posedge clk)
    begin
        if(reset)
        begin
            for(k=0 ; k<32 ; k=k+1)
            begin
                regfile[k] <= 0; // reset all registers to 0
            end
        end
        else 
        begin
            if(write)
            regfile[dr] <= wrdata; // if write is enabled, write data to destination register
        end
    end
endmodule

registerwithreset/test4.v
`include "32bitreg.v"

module regfiletest;
reg [4:0] sr1,sr2,dr; //source and destination register numbers
reg [31:0] wrdata; //data to be written
reg write,reset,clk; //write and reset signals
wire [31:0] rdData1,rdData2; //data to be read from registers
integer k;

regbank_v4 REG (rdData1 , rdData2 , wrdata , sr1 , sr2 , dr , write , reset , clk); //register bank instance    

initial clk = 0;

always #5 clk = ~clk;  //clock genegeration

initial
    begin
        $dumpfile ("test4.vcd");
        $dumpvars (0,regfiletest); //dump file generation
        #1 reset = 1; write = 0;
        #5 reset = 0;
    end
initial
    begin 
        #7
        for (k=0 ; k<32 ; k=k+1)
        begin
            dr = k;
            wrdata = 10*k;
            write = 1; //write enable
            #10 write = 0;
        end
        #20
        for (k=0 ; k<32 ; k=k+2)
        begin
            sr1 = k;
            sr2 = k+1;
            #5;
            $display ("reg[%2d] = %d , reg[%2d] = %d" ,sr1,rdData1,sr2,rdData2);
        end
        #200 $finish; //end simulation
    end
    endmodule

registerwithreset/test4.vcd
$date
	Sun Apr 13 13:03:11 2025
$end
$version
	Icarus Verilog
$end
$timescale
	1s
$end
$scope module regfiletest $end
$var wire 32 ! rdData1 [31:0] $end
$var wire 32 " rdData2 [31:0] $end
$var reg 1 # clk $end
$var reg 5 $ dr [4:0] $end
$var integer 32 % k [31:0] $end
$var reg 1 & reset $end
$var reg 5 ' sr1 [4:0] $end
$var reg 5 ( sr2 [4:0] $end
$var reg 32 ) wrdata [31:0] $end
$var reg 1 * write $end
$scope module REG $end
$var wire 1 + clk $end
$var wire 5 , dr [4:0] $end
$var wire 32 - rdData1 [31:0] $end
$var wire 32 . rdData2 [31:0] $end
$var wire 1 / reset $end
$var wire 5 0 sr1 [4:0] $end
$var wire 5 1 sr2 [4:0] $end
$var wire 32 2 wrdata [31:0] $end
$var wire 1 3 write $end
$var integer 32 4 k [31:0] $end
$upscope $end
$upscope $end
$enddefinitions $end
#0
$dumpvars
bx 4
x3
bx 2
bx 1
bx 0
x/
bx .
bx -
bx ,
0+
x*
bx )
bx (
bx '
x&
bx %
bx $
0#
bx "
bx !
$end
#1
0*
03
1&
1/
#5
b100000 4
1#
1+
#6
0&
0/
#7
1*
13
b0 )
b0 2
b0 $
b0 ,
b0 %
#10
0#
0+
#15
1#
1+
#17
b1010 )
b1010 2
b1 $
b1 ,
b1 %
1*
13
#20
0#
0+
#25
1#
1+
#27
b10100 )
b10100 2
b10 $
b10 ,
b10 %
1*
13
#30
0#
0+
#35
1#
1+
#37
b11110 )
b11110 2
b11 $
b11 ,
b11 %
1*
13
#40
0#
0+
#45
1#
1+
#47
b101000 )
b101000 2
b100 $
b100 ,
b100 %
1*
13
#50
0#
0+
#55
1#
1+
#57
b110010 )
b110010 2
b101 $
b101 ,
b101 %
1*
13
#60
0#
0+
#65
1#
1+
#67
b111100 )
b111100 2
b110 $
b110 ,
b110 %
1*
13
#70
0#
0+
#75
1#
1+
#77
b1000110 )
b1000110 2
b111 $
b111 ,
b111 %
1*
13
#80
0#
0+
#85
1#
1+
#87
b1010000 )
b1010000 2
b1000 $
b1000 ,
b1000 %
1*
13
#90
0#
0+
#95
1#
1+
#97
b1011010 )
b1011010 2
b1001 $
b1001 ,
b1001 %
1*
13
#100
0#
0+
#105
1#
1+
#107
b1100100 )
b1100100 2
b1010 $
b1010 ,
b1010 %
1*
13
#110
0#
0+
#115
1#
1+
#117
b1101110 )
b1101110 2
b1011 $
b1011 ,
b1011 %
1*
13
#120
0#
0+
#125
1#
1+
#127
b1111000 )
b1111000 2
b1100 $
b1100 ,
b1100 %
1*
13
#130
0#
0+
#135
1#
1+
#137
b10000010 )
b10000010 2
b1101 $
b1101 ,
b1101 %
1*
13
#140
0#
0+
#145
1#
1+
#147
b10001100 )
b10001100 2
b1110 $
b1110 ,
b1110 %
1*
13
#150
0#
0+
#155
1#
1+
#157
b10010110 )
b10010110 2
b1111 $
b1111 ,
b1111 %
1*
13
#160
0#
0+
#165
1#
1+
#167
b10100000 )
b10100000 2
b10000 $
b10000 ,
b10000 %
1*
13
#170
0#
0+
#175
1#
1+
#177
b10101010 )
b10101010 2
b10001 $
b10001 ,
b10001 %
1*
13
#180
0#
0+
#185
1#
1+
#187
b10110100 )
b10110100 2
b10010 $
b10010 ,
b10010 %
1*
13
#190
0#
0+
#195
1#
1+
#197
b10111110 )
b10111110 2
b10011 $
b10011 ,
b10011 %
1*
13
#200
0#
0+
#205
1#
1+
#207
b11001000 )
b11001000 2
b10100 $
b10100 ,
b10100 %
1*
13
#210
0#
0+
#215
1#
1+
#217
b11010010 )
b11010010 2
b10101 $
b10101 ,
b10101 %
1*
13
#220
0#
0+
#225
1#
1+
#227
b11011100 )
b11011100 2
b10110 $
b10110 ,
b10110 %
1*
13
#230
0#
0+
#235
1#
1+
#237
b11100110 )
b11100110 2
b10111 $
b10111 ,
b10111 %
1*
13
#240
0#
0+
#245
1#
1+
#247
b11110000 )
b11110000 2
b11000 $
b11000 ,
b11000 %
1*
13
#250
0#
0+
#255
1#
1+
#257
b11111010 )
b11111010 2
b11001 $
b11001 ,
b11001 %
1*
13
#260
0#
0+
#265
1#
1+
#267
b100000100 )
b100000100 2
b11010 $
b11010 ,
b11010 %
1*
13
#270
0#
0+
#275
1#
1+
#277
b100001110 )
b100001110 2
b11011 $
b11011 ,
b11011 %
1*
13
#280
0#
0+
#285
1#
1+
#287
b100011000 )
b100011000 2
b11100 $
b11100 ,
b11100 %
1*
13
#290
0#
0+
#295
1#
1+
#297
b100100010 )
b100100010 2
b11101 $
b11101 ,
b11101 %
1*
13
#300
0#
0+
#305
1#
1+
#307
b100101100 )
b100101100 2
b11110 $
b11110 ,
b11110 %
1*
13
#310
0#
0+
#315
1#
1+
#317
b100110110 )
b100110110 2
b11111 $
b11111 ,
b11111 %
1*
13
#320
0#
0+
#325
1#
1+
#327
b100000 %
0*
03
#330
0#
0+
#335
1#
1+
#340
0#
0+
#345
1#
1+
#347
b1 (
b1 1
b1010 "
b1010 .
b0 '
b0 0
b0 !
b0 -
b0 %
#350
0#
0+
#352
b11 (
b11 1
b11110 "
b11110 .
b10 '
b10 0
b10100 !
b10100 -
b10 %
#355
1#
1+
#357
b101 (
b101 1
b110010 "
b110010 .
b100 '
b100 0
b101000 !
b101000 -
b100 %
#360
0#
0+
#362
b111 (
b111 1
b1000110 "
b1000110 .
b110 '
b110 0
b111100 !
b111100 -
b110 %
#365
1#
1+
#367
b1001 (
b1001 1
b1011010 "
b1011010 .
b1000 '
b1000 0
b1010000 !
b1010000 -
b1000 %
#370
0#
0+
#372
b1011 (
b1011 1
b1101110 "
b1101110 .
b1010 '
b1010 0
b1100100 !
b1100100 -
b1010 %
#375
1#
1+
#377
b1101 (
b1101 1
b10000010 "
b10000010 .
b1100 '
b1100 0
b1111000 !
b1111000 -
b1100 %
#380
0#
0+
#382
b1111 (
b1111 1
b10010110 "
b10010110 .
b1110 '
b1110 0
b10001100 !
b10001100 -
b1110 %
#385
1#
1+
#387
b10001 (
b10001 1
b10101010 "
b10101010 .
b10000 '
b10000 0
b10100000 !
b10100000 -
b10000 %
#390
0#
0+
#392
b10011 (
b10011 1
b10111110 "
b10111110 .
b10010 '
b10010 0
b10110100 !
b10110100 -
b10010 %
#395
1#
1+
#397
b10101 (
b10101 1
b11010010 "
b11010010 .
b10100 '
b10100 0
b11001000 !
b11001000 -
b10100 %
#400
0#
0+
#402
b10111 (
b10111 1
b11100110 "
b11100110 .
b10110 '
b10110 0
b11011100 !
b11011100 -
b10110 %
#405
1#
1+
#407
b11001 (
b11001 1
b11111010 "
b11111010 .
b11000 '
b11000 0
b11110000 !
b11110000 -
b11000 %
#410
0#
0+
#412
b11011 (
b11011 1
b100001110 "
b100001110 .
b11010 '
b11010 0
b100000100 !
b100000100 -
b11010 %
#415
1#
1+
#417
b11101 (
b11101 1
b100100010 "
b100100010 .
b11100 '
b11100 0
b100011000 !
b100011000 -
b11100 %
#420
0#
0+
#422
b11111 (
b11111 1
b100110110 "
b100110110 .
b11110 '
b11110 0
b100101100 !
b100101100 -
b11110 %
#425
1#
1+
#427
b100000 %
